kune/__init__.py
kune/cli.py
kune/kune.py
kune-0.2.3.dist-info/AUTHORS.rst
kune-0.2.3.dist-info/LICENSE
kune-0.2.3.dist-info/METADATA
kune-0.2.3.dist-info/WHEEL
kune-0.2.3.dist-info/entry_points.txt
kune-0.2.3.dist-info/top_level.txt
kune-0.2.3.dist-info/RECORD
