Metadata-Version: 2.1
Name: kune
Version: 0.2.3
Summary: Host your live HTML presentations in sync across many devices.
Home-page: https://github.com/brennan.barker/kune
Author: Brennan Barker
Author-email: 19918186+BrennanBarker@users.noreply.github.com
License: MIT license
Keywords: kune
Platform: UNKNOWN
Classifier: Development Status :: 2 - Pre-Alpha
Classifier: Intended Audience :: Developers
Classifier: License :: OSI Approved :: MIT License
Classifier: Natural Language :: English
Classifier: Programming Language :: Python :: 3
Classifier: Programming Language :: Python :: 3.6
Classifier: Programming Language :: Python :: 3.7
Classifier: Programming Language :: Python :: 3.8
Requires-Python: >=3.6
Requires-Dist: Click (>=7.0)
Requires-Dist: Flask
Requires-Dist: Flask-SocketIO
Requires-Dist: eventlet
